authenticator/__init__.py
authenticator/dataflowairflowauthenticator.py
authenticator/dataflowhubauthenticator.py
authenticator/dataflowsupersetauthenticator.py
dataflow/__init__.py
dataflow/configuration.py
dataflow/database_manager.py
dataflow/dataflow.py
dataflow/db.py
dataflow/environment.py
dataflow/models/__init__.py
dataflow/models/app_types.py
dataflow/models/blacklist_library.py
dataflow/models/connection.py
dataflow/models/connection_type.py
dataflow/models/dataflow_setting.py
dataflow/models/dataflow_zone.py
dataflow/models/environment.py
dataflow/models/environment_status.py
dataflow/models/git_ssh.py
dataflow/models/org_associations.py
dataflow/models/organization.py
dataflow/models/otp.py
dataflow/models/pinned_projects.py
dataflow/models/pod_activity.py
dataflow/models/pod_session_history.py
dataflow/models/project_details.py
dataflow/models/recent_project_studio.py
dataflow/models/recent_projects.py
dataflow/models/role.py
dataflow/models/role_server.py
dataflow/models/role_zone.py
dataflow/models/server_config.py
dataflow/models/session.py
dataflow/models/subscription.py
dataflow/models/team.py
dataflow/models/user.py
dataflow/models/user_team.py
dataflow/models/variables.py
dataflow/schemas/__init__.py
dataflow/schemas/connection.py
dataflow/schemas/git_ssh.py
dataflow/schemas/secret.py
dataflow/scripts/clone_environment.sh
dataflow/scripts/create_environment.sh
dataflow/secrets_manager/__init__.py
dataflow/secrets_manager/factory.py
dataflow/secrets_manager/interface.py
dataflow/secrets_manager/service.py
dataflow/secrets_manager/utils.py
dataflow/secrets_manager/providers/__init__.py
dataflow/secrets_manager/providers/aws_manager.py
dataflow/secrets_manager/providers/azure_manager.py
dataflow/secrets_manager/providers/gcp_manager.py
dataflow/utils/__init__.py
dataflow/utils/blocked_domains.py
dataflow/utils/exceptions.py
dataflow/utils/get_current_user.py
dataflow/utils/logger.py
dfmigration/__init__.py
dfmigration/env.py
dataflow_core-2.1.28.dist-info/METADATA
dataflow_core-2.1.28.dist-info/WHEEL
dataflow_core-2.1.28.dist-info/entry_points.txt
dataflow_core-2.1.28.dist-info/top_level.txt
dataflow_core-2.1.28.dist-info/RECORD
