Metadata-Version: 2.4
Name: dataflow-core
Version: 2.1.28
Summary: Dataflow core package
Author: Dataflow
Author-email: 
Requires-Dist: sqlalchemy
Requires-Dist: alembic
Requires-Dist: boto3
Requires-Dist: psycopg2-binary
Requires-Dist: pymysql
Requires-Dist: requests
Requires-Dist: azure-identity
Requires-Dist: azure-keyvault-secrets
Requires-Dist: google-auth
Requires-Dist: google-cloud-secret-manager
Dynamic: author
Dynamic: requires-dist
Dynamic: summary
